jh_hpc_interface/__init__.py
jh_hpc_interface/jh_environment.py
jh_hpc_interface/jh_interface.py
jh_hpc_interface/config/jh_config.ini
jh_hpc_interface-1.3.data/scripts/jh_slurm_wizard
jh_hpc_interface-1.3.data/scripts/jh_wrapper
jh_hpc_interface-1.3.dist-info/LICENSE
jh_hpc_interface-1.3.dist-info/METADATA
jh_hpc_interface-1.3.dist-info/WHEEL
jh_hpc_interface-1.3.dist-info/top_level.txt
jh_hpc_interface-1.3.dist-info/RECORD
