Metadata-Version: 2.1
Name: jh-hpc-interface
Version: 1.3
Summary: JupyterHub + High-Performace Computing
Home-page: https://github.com/pc2/JHub-HPC-Interface
Author: Paderborn Center for Parallel Computing
License: UNKNOWN
Project-URL: Bug Tracker, https://github.com/pc2/JHub-HPC-Interface/issues
Platform: UNKNOWN
Classifier: Programming Language :: Python :: 3
Classifier: License :: OSI Approved :: MIT License
Requires-Dist: batchspawner
Requires-Dist: notebook
